hilti_profis/__init__.py
hilti_profis/basefile.pe
hilti_profis/main.py
hilti_profis/xmlparser.py
hilti_profis/Config/__init__.py
hilti_profis/Config/main.py
hilti_profis/Model/__init__.py
hilti_profis/Model/main.py
hilti_profis/Model/Anchor/__init__.py
hilti_profis/Model/AnchorLayout/__init__.py
hilti_profis/Model/AnchorLayout/Points/__init__.py
hilti_profis/Model/AnchorPlate/__init__.py
hilti_profis/Model/AnchorPlate/Custom/__init__.py
hilti_profis/Model/AnchorPlate/Ledger/__init__.py
hilti_profis/Model/BaseMaterial/__init__.py
hilti_profis/Model/BaseMaterial/SupplementaryRebar/__init__.py
hilti_profis/Model/Loads/__init__.py
hilti_profis/Model/Loads/Combos/__init__.py
hilti_profis/Model/Options/__init__.py
hilti_profis/Model/Profile/__init__.py
hilti_profis/Model/Profile/Custom/__init__.py
hilti_profis/Model/ShearLug/__init__.py
hilti_profis/Model/Stiffeners/__init__.py
hilti_profis/Model/Stiffeners/Custom/__init__.py
hilti_profis/Model/Welds/__init__.py
hilti_profis/Model/_Template/__init__.py
hilti_profis/utils/logger.py
hilti_profis-0.0.4.dist-info/LICENSE
hilti_profis-0.0.4.dist-info/WHEEL
hilti_profis-0.0.4.dist-info/METADATA
hilti_profis-0.0.4.dist-info/RECORD
