Metadata-Version: 2.3
Name: hilti_profis
Version: 0.0.4
Summary: Python binding for generating `.pe` files, for use with Hilti-Profis software.
Author-email: Arun Kishore <pypi@rpakishore.co.in>
Requires-Python: >=3.11.0
Classifier: License :: OSI Approved :: Mozilla Public License 2.0 (MPL 2.0)
Requires-Dist: xmltodict
Requires-Dist: ipykernel ; extra == "dev"
Requires-Dist: pytest ; extra == "dev"
Project-URL: Home, https://github.com/rpakishore/Hilti-Profis
Provides-Extra: dev
